lektor_broken_links.py
lektor_broken_links-0.2.0.dist-info/LICENSE
lektor_broken_links-0.2.0.dist-info/METADATA
lektor_broken_links-0.2.0.dist-info/WHEEL
lektor_broken_links-0.2.0.dist-info/entry_points.txt
lektor_broken_links-0.2.0.dist-info/top_level.txt
lektor_broken_links-0.2.0.dist-info/RECORD
