Metadata-Version: 2.1
Name: lektor-broken-links
Version: 0.2.0
Summary: Find all the broken links in your Lektor site!
Home-page: https://github.com/RotationMatrix/lektor-broken-links
Author: RotationMatrix
License: MIT-License
Keywords: Lektor broken links plugin
Classifier: Framework :: Lektor
Classifier: Environment :: Plugins
Classifier: License :: OSI Approved :: MIT License
Classifier: Operating System :: OS Independent
Classifier: Programming Language :: Python :: 3
Classifier: Topic :: Internet :: WWW/HTTP :: Site Management :: Link Checking
License-File: LICENSE
Requires-Dist: mistune (<2,>=0.7.0)
Requires-Dist: click (>=7.0)
Requires-Dist: furl (>=2.1.0)
